<?xml version="1.0" encoding="UTF-8"?>
<songs>
	<song>
		<albumid>702</albumid>
		<songid>8527</songid>
		<name>Chúa không lầm (Saxophone)</name>
		<artist>Đông Hòa</artist>
		<author>Lm. Kim Long</author>
		<album>Lời Vọng Tình Yêu (Saxophone)</album>
		<type>Saxophone (Hòa Tấu)</type>
		<audio>http://thanhcavietnam.mobi/FilesNhacKhongLoi/LoiVongTinhYeu(Saxophone)/09.ChuaKhongLam_kl_DongHoa.mp3</audio>
		<pdf>http://thanhcavietnam.mobi/FilesNhacKhongLoi/LoiVongTinhYeu(Saxophone)/ChuaKhongLam_kl.pdf</pdf>
	</song>
	<song>
		<albumid>702</albumid>
		<songid>8526</songid>
		<name>Chứng nhân tình yêu (Saxophone)</name>
		<artist>Đông Hòa</artist>
		<author>Lm. Nguyễn Duy</author>
		<album>Lời Vọng Tình Yêu (Saxophone)</album>
		<type>Saxophone (Hòa Tấu)</type>
		<audio>http://thanhcavietnam.mobi/FilesNhacKhongLoi/LoiVongTinhYeu(Saxophone)/08.ChungNhanTinhYeu_nd_DongHoa.mp3</audio>
		<pdf>http://thanhcavietnam.mobi/FilesNhacKhongLoi/LoiVongTinhYeu(Saxophone)/ChungNhanTinhYeu_nd.pdf</pdf>
	</song>
	<song>
		<albumid>702</albumid>
		<songid>8528</songid>
		<name>Tình Chúa (Saxophone)</name>
		<artist>Đông Hòa</artist>
		<author>Đỗ Thi Thức</author>
		<album>Lời Vọng Tình Yêu (Saxophone)</album>
		<type>Saxophone (Hòa Tấu)</type>
		<audio>http://thanhcavietnam.mobi/FilesNhacKhongLoi/LoiVongTinhYeu(Saxophone)/10.TinhChua_dtt_DongHoa.mp3</audio>
		<pdf>http://thanhcavietnam.mobi/FilesNhacKhongLoi/LoiVongTinhYeu(Saxophone)/TinhChua_dtt.pdf</pdf>
	</song>
	<song>
		<albumid>702</albumid>
		<songid>8520</songid>
		<name>Bỏ Ngài con biết theo ai (Saxophone)</name>
		<artist>Đông Hòa</artist>
		<author>P. Kim</author>
		<album>Lời Vọng Tình Yêu (Saxophone)</album>
		<type>Saxophone (Hòa Tấu)</type>
		<audio>http://thanhcavietnam.mobi/FilesNhacKhongLoi/LoiVongTinhYeu(Saxophone)/02.BoNgaiConBietTheoAi_pk_DongHoa.mp3</audio>
		<pdf>http://thanhcavietnam.mobi/FilesNhacKhongLoi/LoiVongTinhYeu(Saxophone)/BoNgaiConBietTheoAi_pk.pdf</pdf>
	</song>
	<song>
		<albumid>702</albumid>
		<songid>8519</songid>
		<name>Lời vọng tình yêu (Saxophone)</name>
		<artist>Đông Hòa</artist>
		<author>Đỗ Vy Hạ</author>
		<album>Lời Vọng Tình Yêu (Saxophone)</album>
		<type>Saxophone (Hòa Tấu)</type>
		<audio>http://thanhcavietnam.mobi/FilesNhacKhongLoi/LoiVongTinhYeu(Saxophone)/01.LoiVongTinhYeu_dvh_DongHoa.mp3</audio>
		<pdf>http://thanhcavietnam.mobi/FilesNhacKhongLoi/LoiVongTinhYeu(Saxophone)/LoiVongTinhYeu_dvh.pdf</pdf>
	</song>
	<song>
		<albumid>702</albumid>
		<songid>8522</songid>
		<name>Tâm tình ca 3 (Saxophone)</name>
		<artist>Đông Hòa</artist>
		<author>Lm. Thành Tâm</author>
		<album>Lời Vọng Tình Yêu (Saxophone)</album>
		<type>Saxophone (Hòa Tấu)</type>
		<audio>http://thanhcavietnam.mobi/FilesNhacKhongLoi/LoiVongTinhYeu(Saxophone)/04.TamTinhCa3_tt_DongHoa.mp3</audio>
		<pdf>http://thanhcavietnam.mobi/FilesNhacKhongLoi/LoiVongTinhYeu(Saxophone)/TamTinhCa3_tt.pdf</pdf>
	</song>
	<song>
		<albumid>702</albumid>
		<songid>8524</songid>
		<name>Trời đã tối [Nguyện cầu] (Saxophone)</name>
		<artist>Đông Hòa</artist>
		<author>Lm. Thành Tâm</author>
		<album>Lời Vọng Tình Yêu (Saxophone)</album>
		<type>Saxophone (Hòa Tấu)</type>
		<audio>http://thanhcavietnam.mobi/FilesNhacKhongLoi/LoiVongTinhYeu(Saxophone)/06.TroiDaToi_tt_DongHoa.mp3</audio>
		<pdf>http://thanhcavietnam.mobi/FilesNhacKhongLoi/LoiVongTinhYeu(Saxophone)/NguyenCau_tt.pdf</pdf>
	</song>
	<song>
		<albumid>702</albumid>
		<songid>8525</songid>
		<name>Từ rất xa khơi (Saxophone)</name>
		<artist>Đông Hòa</artist>
		<author>Đỗ Vy Hạ</author>
		<album>Lời Vọng Tình Yêu (Saxophone)</album>
		<type>Saxophone (Hòa Tấu)</type>
		<audio>http://thanhcavietnam.mobi/FilesNhacKhongLoi/LoiVongTinhYeu(Saxophone)/07.TuRatXaKhoi_dvh_DongHoa.mp3</audio>
		<pdf>http://thanhcavietnam.mobi/FilesNhacKhongLoi/LoiVongTinhYeu(Saxophone)/TuRatXaKhoi_dvh.pdf</pdf>
	</song>
	<song>
		<albumid>702</albumid>
		<songid>8523</songid>
		<name>Sống trong niềm vui (Saxophone)</name>
		<artist>Đông Hòa</artist>
		<author>Lm. Nguyễn Duy</author>
		<album>Lời Vọng Tình Yêu (Saxophone)</album>
		<type>Saxophone (Hòa Tấu)</type>
		<audio>http://thanhcavietnam.mobi/FilesNhacKhongLoi/LoiVongTinhYeu(Saxophone)/05.SongTrongNiemVui_nd_DongHoa.mp3</audio>
		<pdf>http://thanhcavietnam.mobi/FilesNhacKhongLoi/LoiVongTinhYeu(Saxophone)/SongTrongNiemVui_nd.pdf</pdf>
	</song>
	<song>
		<albumid>702</albumid>
		<songid>8521</songid>
		<name>Yêu thương cho người (Saxophone)</name>
		<artist>Đông Hòa</artist>
		<author>Lm. Duy Thiên</author>
		<album>Lời Vọng Tình Yêu (Saxophone)</album>
		<type>Saxophone (Hòa Tấu)</type>
		<audio>http://thanhcavietnam.mobi/FilesNhacKhongLoi/LoiVongTinhYeu(Saxophone)/03.YeuThuongChoNguoi_dt_DongHoa.mp3</audio>
		<pdf>http://thanhcavietnam.mobi/FilesNhacKhongLoi/LoiVongTinhYeu(Saxophone)/YeuThuongChoNguoi_dt.pdf</pdf>
	</song>
	<song>
		<albumid>707</albumid>
		<songid>8554</songid>
		<name>Cầu cho Cha Mẹ 1 (Saxophone)</name>
		<artist>Phạm Quang Trung</artist>
		<author>Phanxicô</author>
		<album>Tình Yêu Thiên Chúa (Saxophone)</album>
		<type>Saxophone (Hòa Tấu)</type>
		<audio>http://thanhcavietnam.mobi/FilesNhacKhongLoi/TinhYeuThienChua(Saxophone)/10.CauChoChaMe1_pxc_PhamQuangTrung.mp3</audio>
		<pdf>http://thanhcavietnam.mobi/FilesNhacKhongLoi/TinhYeuThienChua(Saxophone)/CauChoChaMe1_pxc.pdf</pdf>
	</song>
	<song>
		<albumid>707</albumid>
		<songid>8545</songid>
		<name>Tình yêu Thiên Chúa (Saxophone)</name>
		<artist>Phạm Quang Trung</artist>
		<author>Thế Thông - Đình Diễn</author>
		<album>Tình Yêu Thiên Chúa (Saxophone)</album>
		<type>Saxophone (Hòa Tấu)</type>
		<audio>http://thanhcavietnam.mobi/FilesNhacKhongLoi/TinhYeuThienChua(Saxophone)/01.TinhYeuThienChua_tth-dd_PhamQuangTrung.mp3</audio>
		<pdf>http://thanhcavietnam.mobi/FilesNhacKhongLoi/TinhYeuThienChua(Saxophone)/TinhYeuThienChua-tth-dd.pdf</pdf>
	</song>
	<song>
		<albumid>707</albumid>
		<songid>8549</songid>
		<name>Bỏ Ngài con biết theo ai (Saxophone)</name>
		<artist>Phạm Quang Trung</artist>
		<author>P. Kim</author>
		<album>Tình Yêu Thiên Chúa (Saxophone)</album>
		<type>Saxophone (Hòa Tấu)</type>
		<audio>http://thanhcavietnam.mobi/FilesNhacKhongLoi/TinhYeuThienChua(Saxophone)/05.BoNgaiConBietTheoAi_pk_PhamQuangTrung.mp3</audio>
		<pdf>http://thanhcavietnam.mobi/FilesNhacKhongLoi/TinhYeuThienChua(Saxophone)/BoNgaiConBietTheoAi_pk.pdf</pdf>
	</song>
	<song>
		<albumid>707</albumid>
		<songid>8552</songid>
		<name>Dâng Ngài (Saxophone)</name>
		<artist>Phạm Quang Trung</artist>
		<author>Thy Yên</author>
		<album>Tình Yêu Thiên Chúa (Saxophone)</album>
		<type>Saxophone (Hòa Tấu)</type>
		<audio>http://thanhcavietnam.mobi/FilesNhacKhongLoi/TinhYeuThienChua(Saxophone)/08.DangNgai_ty_PhamQuangTrung.mp3</audio>
		<pdf>http://thanhcavietnam.mobi/FilesNhacKhongLoi/TinhYeuThienChua(Saxophone)/DangNgai_ty.pdf</pdf>
	</song>
	<song>
		<albumid>707</albumid>
		<songid>8551</songid>
		<name>Sống trong niềm vui (Saxophone)</name>
		<artist>Phạm Quang Trung</artist>
		<author>Lm. Nguyễn Duy</author>
		<album>Tình Yêu Thiên Chúa (Saxophone)</album>
		<type>Saxophone (Hòa Tấu)</type>
		<audio>http://thanhcavietnam.mobi/FilesNhacKhongLoi/TinhYeuThienChua(Saxophone)/07.SongTrongNiemVui_nd_PhamQuangTrung.mp3</audio>
		<pdf>http://thanhcavietnam.mobi/FilesNhacKhongLoi/TinhYeuThienChua(Saxophone)/SongTrongNiemVui_nd.pdf</pdf>
	</song>
	<song>
		<albumid>707</albumid>
		<songid>8546</songid>
		<name>Cầu cho Cha Mẹ 2 (Saxophone)</name>
		<artist>Phạm Quang Trung</artist>
		<author>Phanxicô</author>
		<album>Tình Yêu Thiên Chúa (Saxophone)</album>
		<type>Saxophone (Hòa Tấu)</type>
		<audio>http://thanhcavietnam.mobi/FilesNhacKhongLoi/TinhYeuThienChua(Saxophone)/02.CauChoChaMe2_pxc_PhamQuangTrung.mp3</audio>
		<pdf>http://thanhcavietnam.mobi/FilesNhacKhongLoi/TinhYeuThienChua(Saxophone)/CauChoChaMe2_pxc.pdf</pdf>
	</song>
	<song>
		<albumid>707</albumid>
		<songid>8547</songid>
		<name>Cong dâng Chúa - Lễ dâng (Saxophone)</name>
		<artist>Phạm Quang Trung</artist>
		<author>Lm. Nguyễn Mộng Huỳnh</author>
		<album>Tình Yêu Thiên Chúa (Saxophone)</album>
		<type>Saxophone (Hòa Tấu)</type>
		<audio>http://thanhcavietnam.mobi/FilesNhacKhongLoi/TinhYeuThienChua(Saxophone)/03.ConDangChua_nmh_PhamQuangTrung.mp3</audio>
		<pdf>http://thanhcavietnam.mobi/FilesNhacKhongLoi/TinhYeuThienChua(Saxophone)/LeDang_nmh.pdf</pdf>
	</song>
	<song>
		<albumid>707</albumid>
		<songid>8550</songid>
		<name>Cầu cho Cha Mẹ 8 (Saxophone)</name>
		<artist>Phạm Quang Trung</artist>
		<author>Phanxicô</author>
		<album>Tình Yêu Thiên Chúa (Saxophone)</album>
		<type>Saxophone (Hòa Tấu)</type>
		<audio>http://thanhcavietnam.mobi/FilesNhacKhongLoi/TinhYeuThienChua(Saxophone)/06.CauChoChaMe8_pxc_PhamQuangTrung.mp3</audio>
		<pdf>http://thanhcavietnam.mobi/FilesNhacKhongLoi/TinhYeuThienChua(Saxophone)/CauChoChaMe8_pxc.pdf</pdf>
	</song>
	<song>
		<albumid>707</albumid>
		<songid>8548</songid>
		<name>Cầu cho Cha Mẹ 7 (Saxophone)</name>
		<artist>Phạm Quang Trung</artist>
		<author>Phanxicô</author>
		<album>Tình Yêu Thiên Chúa (Saxophone)</album>
		<type>Saxophone (Hòa Tấu)</type>
		<audio>http://thanhcavietnam.mobi/FilesNhacKhongLoi/TinhYeuThienChua(Saxophone)/04.CauChoChaMe7_pxc_PhamQuangTrung.mp3</audio>
		<pdf>http://thanhcavietnam.mobi/FilesNhacKhongLoi/TinhYeuThienChua(Saxophone)/CauChoChaMe7_pxc.pdf</pdf>
	</song>
	<song>
		<albumid>707</albumid>
		<songid>8553</songid>
		<name>Cơn cám dỗ (Saxophone)</name>
		<artist>Phạm Quang Trung</artist>
		<author>Ý Vũ</author>
		<album>Tình Yêu Thiên Chúa (Saxophone)</album>
		<type>Saxophone (Hòa Tấu)</type>
		<audio>http://thanhcavietnam.mobi/FilesNhacKhongLoi/TinhYeuThienChua(Saxophone)/09.ConCamDo_yv_PhamQuangTrung.mp3</audio>
		<pdf></pdf>
	</song>
	<song>
		<albumid>787</albumid>
		<songid>9433</songid>
		<name>Lời con xin Chúa (Saxophone)</name>
		<artist>Đông Hòa</artist>
		<author>Lê Kim Khánh</author>
		<album>Giáng Sinh Lại về (Saxophone)</album>
		<type>Saxophone (Hòa Tấu)</type>
		<audio>http://thanhcavietnam.mobi/FilesNhacKhongLoi/GiangSinhLaiVe(Saxophone)/10.LoiConXinChua_lkk_DongHoa.mp3</audio>
		<pdf>http://thanhcavietnam.mobi/FilesNhacKhongLoi/GiangSinhLaiVe(Saxophone)/LoiConXinChua_lkk.pdf</pdf>
	</song>
	<song>
		<albumid>787</albumid>
		<songid>9426</songid>
		<name>Cao cung lên (Saxophone)</name>
		<artist>Đông Hòa</artist>
		<author>Nguyễn Khắc Xuyên - Lm. Hoài Đức</author>
		<album>Giáng Sinh Lại về (Saxophone)</album>
		<type>Saxophone (Hòa Tấu)</type>
		<audio>http://thanhcavietnam.mobi/FilesNhacKhongLoi/GiangSinhLaiVe(Saxophone)/03.CaoCungLen_nkx-hd_DongHoa.mp3</audio>
		<pdf>http://thanhcavietnam.mobi/FilesNhacKhongLoi/GiangSinhLaiVe(Saxophone)/CaoCungLen_nkx-hd.pdf</pdf>
	</song>
	<song>
		<albumid>787</albumid>
		<songid>9427</songid>
		<name>Bài Thánh ca buồn (Saxophone)</name>
		<artist>Đông Hòa</artist>
		<author>Nguyễn Vũ</author>
		<album>Giáng Sinh Lại về (Saxophone)</album>
		<type>Saxophone (Hòa Tấu)</type>
		<audio>http://thanhcavietnam.mobi/FilesNhacKhongLoi/GiangSinhLaiVe(Saxophone)/04.BaiThanhCaBuon_nv_DongHoa.mp3</audio>
		<pdf>http://thanhcavietnam.mobi/FilesNhacKhongLoi/GiangSinhLaiVe(Saxophone)/BaiThanhCaBuon_nv.pdf</pdf>
	</song>
	<song>
		<albumid>787</albumid>
		<songid>9431</songid>
		<name>Tình người ngoại đạo (Saxophone)</name>
		<artist>Đông Hòa</artist>
		<author>Nguyễn Văn Đông (Phượng Linh)</author>
		<album>Giáng Sinh Lại về (Saxophone)</album>
		<type>Saxophone (Hòa Tấu)</type>
		<audio>http://thanhcavietnam.mobi/FilesNhacKhongLoi/GiangSinhLaiVe(Saxophone)/08.TinhNguoiNgoaiDao_pl_DongHoa.mp3</audio>
		<pdf></pdf>
	</song>
	<song>
		<albumid>787</albumid>
		<songid>9432</songid>
		<name>Holly Night (Saxophone)</name>
		<artist>Đông Hòa</artist>
		<author>Adolphe Charles Adam</author>
		<album>Giáng Sinh Lại về (Saxophone)</album>
		<type>Saxophone (Hòa Tấu)</type>
		<audio>http://thanhcavietnam.mobi/FilesNhacKhongLoi/GiangSinhLaiVe(Saxophone)/09.HollyNight_A.Adam_DongHoa.mp3</audio>
		<pdf></pdf>
	</song>
	<song>
		<albumid>787</albumid>
		<songid>9429</songid>
		<name>Dư âm mùa Giáng Sinh (Saxophone)</name>
		<artist>Đông Hòa</artist>
		<author>Ngân Giang</author>
		<album>Giáng Sinh Lại về (Saxophone)</album>
		<type>Saxophone (Hòa Tấu)</type>
		<audio>http://thanhcavietnam.mobi/FilesNhacKhongLoi/GiangSinhLaiVe(Saxophone)/06.DuAmMuaGiangSinh_ng_DongHoa.mp3</audio>
		<pdf>http://thanhcavietnam.mobi/FilesNhacKhongLoi/GiangSinhLaiVe(Saxophone)/DuAmMuaGiangSinh_ng.pdf</pdf>
	</song>
	<song>
		<albumid>787</albumid>
		<songid>9425</songid>
		<name>Mùa sao sáng (Saxophone)</name>
		<artist>Đông Hòa</artist>
		<author>Nguyễn Văn Đông (Phượng Linh)</author>
		<album>Giáng Sinh Lại về (Saxophone)</album>
		<type>Saxophone (Hòa Tấu)</type>
		<audio>http://thanhcavietnam.mobi/FilesNhacKhongLoi/GiangSinhLaiVe(Saxophone)/02.MuaSaoSang_nvd_DongHoa.mp3</audio>
		<pdf>http://thanhcavietnam.mobi/FilesNhacKhongLoi/GiangSinhLaiVe(Saxophone)/MuaSaoSang_nvd.pdf</pdf>
	</song>
	<song>
		<albumid>787</albumid>
		<songid>9424</songid>
		<name>Silent Night (Saxophone)</name>
		<artist>Đông Hòa</artist>
		<author>F. Gruber</author>
		<album>Giáng Sinh Lại về (Saxophone)</album>
		<type>Saxophone (Hòa Tấu)</type>
		<audio>http://thanhcavietnam.mobi/FilesNhacKhongLoi/GiangSinhLaiVe(Saxophone)/01.SilentNight_F.Gruber_DongHoa.mp3</audio>
		<pdf></pdf>
	</song>
	<song>
		<albumid>787</albumid>
		<songid>9428</songid>
		<name>Mùa hoa tuyết (Saxophone)</name>
		<artist>Đông Hòa</artist>
		<author>Xuân Điềm</author>
		<album>Giáng Sinh Lại về (Saxophone)</album>
		<type>Saxophone (Hòa Tấu)</type>
		<audio>http://thanhcavietnam.mobi/FilesNhacKhongLoi/GiangSinhLaiVe(Saxophone)/05.MuaHoaTuyet_xd_DongHoa.mp3</audio>
		<pdf></pdf>
	</song>
	<song>
		<albumid>787</albumid>
		<songid>9430</songid>
		<name>Santa Claus Is Coming To Town (Saxophone)</name>
		<artist>Đông Hòa</artist>
		<author>J. Fred Coots &amp; Henry Gillespie</author>
		<album>Giáng Sinh Lại về (Saxophone)</album>
		<type>Saxophone (Hòa Tấu)</type>
		<audio>http://thanhcavietnam.mobi/FilesNhacKhongLoi/GiangSinhLaiVe(Saxophone)/07.SantaClausIsComingToTown_DongHoa.mp3</audio>
		<pdf></pdf>
	</song>
	<song>
		<albumid>895</albumid>
		<songid>10914</songid>
		<name>We Wish You A Merry Christmas - Chúc Mừng Giáng Sinh (Saxophone)</name>
		<artist>Phạm Quang Trung</artist>
		<author>Nhạc Noel Quốc Tế</author>
		<album>Đêm Thánh Vô Cùng (Saxophone)</album>
		<type>Saxophone (Hòa Tấu)</type>
		<audio>http://thanhcavietnam.mobi/FilesNhacKhongLoi/DemThanhVoCung(Saxophone)/12.WeWishYouAMerryChristmas_PhamQuangTrung.mp3</audio>
		<pdf></pdf>
	</song>
	<song>
		<albumid>895</albumid>
		<songid>10913</songid>
		<name>Christmas Songs - Hát với mùa Giáng Sinh (Saxophone)</name>
		<artist>Phạm Quang Trung</artist>
		<author>Nhạc Noel Quốc Tế</author>
		<album>Đêm Thánh Vô Cùng (Saxophone)</album>
		<type>Saxophone (Hòa Tấu)</type>
		<audio>http://thanhcavietnam.mobi/FilesNhacKhongLoi/DemThanhVoCung(Saxophone)/11.ChristmasSongs_PhamQuangTrung.mp3</audio>
		<pdf></pdf>
	</song>
	<song>
		<albumid>895</albumid>
		<songid>10903</songid>
		<name>Jingle Bell - Tiếng chuông ngân (Saxophone)</name>
		<artist>Phạm Quang Trung</artist>
		<author>J. Pierpont</author>
		<album>Đêm Thánh Vô Cùng (Saxophone)</album>
		<type>Saxophone (Hòa Tấu)</type>
		<audio>http://thanhcavietnam.mobi/FilesNhacKhongLoi/DemThanhVoCung(Saxophone)/01.JingleBell_JP_PhamQuangTrung.mp3</audio>
		<pdf>http://thanhcavietnam.mobi/FilesNhacKhongLoi/DemThanhVoCung(Saxophone)/JingleBells_J.Pierpont.pdf</pdf>
	</song>
	<song>
		<albumid>895</albumid>
		<songid>10909</songid>
		<name>Silent Night - Đêm yên bình (Saxophone)</name>
		<artist>Phạm Quang Trung</artist>
		<author>Nhạc Noel Quốc Tế</author>
		<album>Đêm Thánh Vô Cùng (Saxophone)</album>
		<type>Saxophone (Hòa Tấu)</type>
		<audio>http://thanhcavietnam.mobi/FilesNhacKhongLoi/DemThanhVoCung(Saxophone)/07.SilentNight_PhamQuangTrung.mp3</audio>
		<pdf></pdf>
	</song>
	<song>
		<albumid>895</albumid>
		<songid>10911</songid>
		<name>The Holy Grace Night - Đêm Hồng Ân (Saxophone)</name>
		<artist>Phạm Quang Trung</artist>
		<author>Nhạc Noel Quốc Tế</author>
		<album>Đêm Thánh Vô Cùng (Saxophone)</album>
		<type>Saxophone (Hòa Tấu)</type>
		<audio>http://thanhcavietnam.mobi/FilesNhacKhongLoi/DemThanhVoCung(Saxophone)/09.TheHolyGraceNight_PhamQuangTrung.mp3</audio>
		<pdf></pdf>
	</song>
	<song>
		<albumid>895</albumid>
		<songid>10912</songid>
		<name>The Holy Grace Songs - Tiếng hát Thánh Ân (Saxophone)</name>
		<artist>Phạm Quang Trung</artist>
		<author>Nhạc Noel Quốc Tế</author>
		<album>Đêm Thánh Vô Cùng (Saxophone)</album>
		<type>Saxophone (Hòa Tấu)</type>
		<audio>http://thanhcavietnam.mobi/FilesNhacKhongLoi/DemThanhVoCung(Saxophone)/10.TheHolyGraceSongs_PhamQuangTrung.mp3</audio>
		<pdf></pdf>
	</song>
	<song>
		<albumid>895</albumid>
		<songid>10907</songid>
		<name>The Church Bell Of Those Days - Chuông Giáo Đường ngày ấy (Saxophone)</name>
		<artist>Phạm Quang Trung</artist>
		<author>Nhạc Noel Quốc Tế</author>
		<album>Đêm Thánh Vô Cùng (Saxophone)</album>
		<type>Saxophone (Hòa Tấu)</type>
		<audio>http://thanhcavietnam.mobi/FilesNhacKhongLoi/DemThanhVoCung(Saxophone)/05.TheChurchBellOfThoseDays_PhamQuangTrung.mp3</audio>
		<pdf></pdf>
	</song>
	<song>
		<albumid>895</albumid>
		<songid>10906</songid>
		<name>Joy To The World - Chúc mừng cho Thế giới (Saxophone)</name>
		<artist>Phạm Quang Trung</artist>
		<author>Nhạc Noel Quốc Tế</author>
		<album>Đêm Thánh Vô Cùng (Saxophone)</album>
		<type>Saxophone (Hòa Tấu)</type>
		<audio>http://thanhcavietnam.mobi/FilesNhacKhongLoi/DemThanhVoCung(Saxophone)/04.JoyToTheWorld_PhamQuangTrung.mp3</audio>
		<pdf></pdf>
	</song>
	<song>
		<albumid>895</albumid>
		<songid>10905</songid>
		<name>Marche De Rois - Huyền thoại những vì sao (Saxophone)</name>
		<artist>Phạm Quang Trung</artist>
		<author>Nhạc Noel Quốc Tế</author>
		<album>Đêm Thánh Vô Cùng (Saxophone)</album>
		<type>Saxophone (Hòa Tấu)</type>
		<audio>http://thanhcavietnam.mobi/FilesNhacKhongLoi/DemThanhVoCung(Saxophone)/03.MarcheDeRois_PhamQuangTrung.mp3</audio>
		<pdf></pdf>
	</song>
	<song>
		<albumid>895</albumid>
		<songid>10910</songid>
		<name>The First Noel - Noel đầu tiên (Saxophone)</name>
		<artist>Phạm Quang Trung</artist>
		<author>Nhạc Noel Quốc Tế</author>
		<album>Đêm Thánh Vô Cùng (Saxophone)</album>
		<type>Saxophone (Hòa Tấu)</type>
		<audio>http://thanhcavietnam.mobi/FilesNhacKhongLoi/DemThanhVoCung(Saxophone)/08.TheFirstNoel_PhamQuangTrung.mp3</audio>
		<pdf></pdf>
	</song>
	<song>
		<albumid>895</albumid>
		<songid>10908</songid>
		<name>Season&apos;s Greeting - Chúc mùa Noel (Saxophone)</name>
		<artist>Phạm Quang Trung</artist>
		<author>Nhạc Noel Quốc Tế</author>
		<album>Đêm Thánh Vô Cùng (Saxophone)</album>
		<type>Saxophone (Hòa Tấu)</type>
		<audio>http://thanhcavietnam.mobi/FilesNhacKhongLoi/DemThanhVoCung(Saxophone)/06.SeasonsGreeting_PhamQuangTrung.mp3</audio>
		<pdf></pdf>
	</song>
	<song>
		<albumid>895</albumid>
		<songid>10904</songid>
		<name>What Child Is This - Hài Nhi là ai (Saxophone)</name>
		<artist>Phạm Quang Trung</artist>
		<author>Nhạc Noel Quốc Tế</author>
		<album>Đêm Thánh Vô Cùng (Saxophone)</album>
		<type>Saxophone (Hòa Tấu)</type>
		<audio>http://thanhcavietnam.mobi/FilesNhacKhongLoi/DemThanhVoCung(Saxophone)/02.WhatChildIsThis_PhamQuangTrung.mp3</audio>
		<pdf></pdf>
	</song>
	<song>
		<albumid>1031</albumid>
		<songid>12596</songid>
		<name>Diễm tình ca 3 (Saxophone)</name>
		<artist>Phạm Quang Trung</artist>
		<author>Lm. Thành Tâm</author>
		<album>Nguyện Cầu Cho Nhau (Hòa Tấu)</album>
		<type>Saxophone (Hòa Tấu)</type>
		<audio>http://thanhcavietnam.net/ThanhCaVN/index.php?url=Download,12596,RP89-F9DE6853E88570FA</audio>
		<pdf>http://thanhcavietnam.mobi/FilesNhacKhongLoi/NguyenCauChoNhau(HoaTau)/DiemTinhCa3_tt.pdf</pdf>
	</song>
	<song>
		<albumid>1031</albumid>
		<songid>12595</songid>
		<name>Nguyện cầu cho nhau (Saxophone)</name>
		<artist>Phạm Quang Trung</artist>
		<author>Phanxicô</author>
		<album>Nguyện Cầu Cho Nhau (Hòa Tấu)</album>
		<type>Saxophone (Hòa Tấu)</type>
		<audio>http://thanhcavietnam.net/ThanhCaVN/index.php?url=Download,12595,RP89-EFA98C34D704BCF7</audio>
		<pdf>http://thanhcavietnam.mobi/FilesNhacKhongLoi/NguyenCauChoNhau(HoaTau)/NguyenCauChoNhau_pxc.pdf</pdf>
	</song>
	<song>
		<albumid>1031</albumid>
		<songid>12603</songid>
		<name>Nhã ca (Saxophone)</name>
		<artist>Phạm Quang Trung</artist>
		<author>Lm. Nguyễn Văn Trinh</author>
		<album>Nguyện Cầu Cho Nhau (Hòa Tấu)</album>
		<type>Saxophone (Hòa Tấu)</type>
		<audio>http://thanhcavietnam.net/ThanhCaVN/index.php?url=Download,12603,RP89-8A659B1324915BF2</audio>
		<pdf>http://thanhcavietnam.mobi/FilesNhacKhongLoi/NguyenCauChoNhau(HoaTau)/NhaCa_nvtr.pdf</pdf>
	</song>
	<song>
		<albumid>1031</albumid>
		<songid>12601</songid>
		<name>Xin định nghĩa tình yêu (Saxophone)</name>
		<artist>Phạm Quang Trung</artist>
		<author>Cao Huy Hoàng</author>
		<album>Nguyện Cầu Cho Nhau (Hòa Tấu)</album>
		<type>Saxophone (Hòa Tấu)</type>
		<audio>http://thanhcavietnam.net/ThanhCaVN/index.php?url=Download,12601,RP89-DD5E150D8A9225FE</audio>
		<pdf>http://thanhcavietnam.mobi/FilesNhacKhongLoi/NguyenCauChoNhau(HoaTau)/XinDinhNghiaTinhYeu_chh.pdf</pdf>
	</song>
	<song>
		<albumid>1031</albumid>
		<songid>12597</songid>
		<name>Khi hoa nở miền Cana (Saxophone)</name>
		<artist>Phạm Quang Trung</artist>
		<author>Phanxicô</author>
		<album>Nguyện Cầu Cho Nhau (Hòa Tấu)</album>
		<type>Saxophone (Hòa Tấu)</type>
		<audio>http://thanhcavietnam.net/ThanhCaVN/index.php?url=Download,12597,RP89-FCC8488186683224</audio>
		<pdf>http://thanhcavietnam.mobi/FilesNhacKhongLoi/NguyenCauChoNhau(HoaTau)/KhiHoaNoMienCana_pxc.pdf</pdf>
	</song>
	<song>
		<albumid>1031</albumid>
		<songid>12598</songid>
		<name>Chung kết trầu cau (Saxophone)</name>
		<artist>Phạm Quang Trung</artist>
		<author>Phanxicô</author>
		<album>Nguyện Cầu Cho Nhau (Hòa Tấu)</album>
		<type>Saxophone (Hòa Tấu)</type>
		<audio>http://thanhcavietnam.net/ThanhCaVN/index.php?url=Download,12598,RP89-03CC9BFC30DF3D82</audio>
		<pdf>http://thanhcavietnam.mobi/FilesNhacKhongLoi/NguyenCauChoNhau(HoaTau)/ChungKetTrauCau_pxc.pdf</pdf>
	</song>
	<song>
		<albumid>1031</albumid>
		<songid>12600</songid>
		<name>Nguyện ước cho tình yêu (Saxophone)</name>
		<artist>Phạm Quang Trung</artist>
		<author>Lm. Nguyễn Duy</author>
		<album>Nguyện Cầu Cho Nhau (Hòa Tấu)</album>
		<type>Saxophone (Hòa Tấu)</type>
		<audio>http://thanhcavietnam.net/ThanhCaVN/index.php?url=Download,12600,RP89-3520D29E69F6EB3A</audio>
		<pdf>http://thanhcavietnam.mobi/FilesNhacKhongLoi/NguyenCauChoNhau(HoaTau)/NguyenUocChoTinhYeu_nd.pdf</pdf>
	</song>
	<song>
		<albumid>1031</albumid>
		<songid>12602</songid>
		<name>Hoa hồng (Saxophone)</name>
		<artist>Phạm Quang Trung</artist>
		<author>Phanxicô</author>
		<album>Nguyện Cầu Cho Nhau (Hòa Tấu)</album>
		<type>Saxophone (Hòa Tấu)</type>
		<audio>http://thanhcavietnam.net/ThanhCaVN/index.php?url=Download,12602,RP89-8AAC6CBF59B899F7</audio>
		<pdf>http://thanhcavietnam.mobi/FilesNhacKhongLoi/NguyenCauChoNhau(HoaTau)/HoaHong_pxc.pdf</pdf>
	</song>
	<song>
		<albumid>1031</albumid>
		<songid>12599</songid>
		<name>Yêu thương đơm hoa kết trái (Saxophone)</name>
		<artist>Phạm Quang Trung</artist>
		<author>Phanxicô</author>
		<album>Nguyện Cầu Cho Nhau (Hòa Tấu)</album>
		<type>Saxophone (Hòa Tấu)</type>
		<audio>http://thanhcavietnam.net/ThanhCaVN/index.php?url=Download,12599,RP89-E7A5BE4C6A40636B</audio>
		<pdf>http://thanhcavietnam.mobi/FilesNhacKhongLoi/NguyenCauChoNhau(HoaTau)/YeuThuongDuomHoaKetTrai_pxc.pdf</pdf>
	</song>
	<song>
		<albumid>1036</albumid>
		<songid>12661</songid>
		<name>Tình Chúa trong đời (Saxophone)</name>
		<artist>Bến Thành Studio</artist>
		<author>Lm. Nguyên Hòa</author>
		<album>Ngàn Đời Xin Ca Ngợi (Hòa tấu)</album>
		<type>Saxophone (Hòa Tấu)</type>
		<audio>http://thanhcavietnam.mobi/FilesNhacKhongLoi/NganDoiXinCaNgoi(HoaTau)/13.TinhChuaTrongDoi_nh_Saxophone.mp3</audio>
		<pdf>http://thanhcavietnam.mobi/FilesNhacKhongLoi/NganDoiXinCaNgoi(HoaTau)/TinhChuaTrongDoi_nh.pdf</pdf>
	</song>
	<song>
		<albumid>1036</albumid>
		<songid>12658</songid>
		<name>Yêu thương một đời (Saxophone)</name>
		<artist>Bến Thành Studio</artist>
		<author>Lm. Nguyên Hòa</author>
		<album>Ngàn Đời Xin Ca Ngợi (Hòa tấu)</album>
		<type>Saxophone (Hòa Tấu)</type>
		<audio>http://thanhcavietnam.mobi/FilesNhacKhongLoi/NganDoiXinCaNgoi(HoaTau)/10.YeuThuongMotDoi_nh_Saxophone.mp3</audio>
		<pdf></pdf>
	</song>
	<song>
		<albumid>1036</albumid>
		<songid>12656</songid>
		<name>Tình yêu là lẽ sống (Saxophone)</name>
		<artist>Bến Thành Studio</artist>
		<author>Lm. Nguyên Hòa</author>
		<album>Ngàn Đời Xin Ca Ngợi (Hòa tấu)</album>
		<type>Saxophone (Hòa Tấu)</type>
		<audio>http://thanhcavietnam.mobi/FilesNhacKhongLoi/NganDoiXinCaNgoi(HoaTau)/08.TinhYeuLaLeSong_nh_Saxophone.mp3</audio>
		<pdf>http://thanhcavietnam.mobi/FilesNhacKhongLoi/NganDoiXinCaNgoi(HoaTau)/TinhYeuLaLeSong_nh.pdf</pdf>
	</song>
	<song>
		<albumid>1036</albumid>
		<songid>12652</songid>
		<name>Ngàn đời xin ca ngợi (Saxophone)</name>
		<artist>Bến Thành Studio</artist>
		<author>Lm. Nguyên Hòa</author>
		<album>Ngàn Đời Xin Ca Ngợi (Hòa tấu)</album>
		<type>Saxophone (Hòa Tấu)</type>
		<audio>http://thanhcavietnam.mobi/FilesNhacKhongLoi/NganDoiXinCaNgoi(HoaTau)/04.NganDoiXinCaNgoi_nh_Saxophone.mp3</audio>
		<pdf></pdf>
	</song>
	<song>
		<albumid>1036</albumid>
		<songid>12649</songid>
		<name>Ánh mắt Ngài yêu thương (Saxophone)</name>
		<artist>Bến Thành Studio</artist>
		<author>Lm. Nguyên Hòa</author>
		<album>Ngàn Đời Xin Ca Ngợi (Hòa tấu)</album>
		<type>Saxophone (Hòa Tấu)</type>
		<audio>http://thanhcavietnam.mobi/FilesNhacKhongLoi/NganDoiXinCaNgoi(HoaTau)/01.AnhMatNgaiYeuThuong_nh_Saxophone.mp3</audio>
		<pdf>http://thanhcavietnam.mobi/FilesNhacKhongLoi/NganDoiXinCaNgoi(HoaTau)/AnhMatNgaiYeuThuong_nh.pdf</pdf>
	</song>
	<song>
		<albumid>1136</albumid>
		<songid>13987</songid>
		<name>Tìm về Chân Thiện Mỹ (Saxophone)</name>
		<artist>Đông Hòa</artist>
		<author>Nguyên Kha</author>
		<album>Lắng Nghe Lời Chúa (Saxophone)</album>
		<type>Saxophone (Hòa Tấu)</type>
		<audio>http://thanhcavietnam.net/ThanhCaVN/index.php?url=Download,13987,RP89-E870382585AB70AA</audio>
		<pdf>http://thanhcavietnam.mobi/FilesNhacKhongLoi/LangNgheLoiChua(Saxophone)/TimVeChanThienMy_nk.pdf</pdf>
	</song>
	<song>
		<albumid>1136</albumid>
		<songid>13986</songid>
		<name>Tâm tình hiến dâng (Saxophone)</name>
		<artist>Đông Hòa</artist>
		<author>Lm. Oanh Sông Lam</author>
		<album>Lắng Nghe Lời Chúa (Saxophone)</album>
		<type>Saxophone (Hòa Tấu)</type>
		<audio>http://113.171.224.206:80/videoplayer/11.TamTinhHienDang_osl_DongHoa.mp3?ich_u_r_i=1876f61db0b2a6e481aed7d2746937ef&amp;ich_s_t_a_r_t=0&amp;ich_e_n_d=0&amp;ich_k_e_y=1345018910751563112463&amp;ich_t_y_p_e=1&amp;ich_d_i_s_k_i_d=4&amp;ich_u_n_i_t=1</audio>
		<pdf>http://thanhcavietnam.mobi/FilesNhacKhongLoi/LangNgheLoiChua(Saxophone)/TamTinhHienDang_osl.pdf</pdf>
	</song>
	<song>
		<albumid>1136</albumid>
		<songid>13985</songid>
		<name>Trông cậy Chúa (Saxophone)</name>
		<artist>Đông Hòa</artist>
		<author>Lm. Nguyễn Duy</author>
		<album>Lắng Nghe Lời Chúa (Saxophone)</album>
		<type>Saxophone (Hòa Tấu)</type>
		<audio>http://thanhcavietnam.mobi/FilesNhacKhongLoi/LangNgheLoiChua(Saxophone)/10.TrongCayChua_nd_DongHoa.mp3</audio>
		<pdf>http://thanhcavietnam.mobi/FilesNhacKhongLoi/LangNgheLoiChua(Saxophone)/TrongCayChua_nd.pdf</pdf>
	</song>
	<song>
		<albumid>1136</albumid>
		<songid>13982</songid>
		<name>Chúa là con đường (Saxophone)</name>
		<artist>Đông Hòa</artist>
		<author>Phanxicô</author>
		<album>Lắng Nghe Lời Chúa (Saxophone)</album>
		<type>Saxophone (Hòa Tấu)</type>
		<audio>http://thanhcavietnam.mobi/FilesNhacKhongLoi/LangNgheLoiChua(Saxophone)/07.ChuaLaConDuong_pxc_DongHoa.mp3</audio>
		<pdf>http://thanhcavietnam.mobi/FilesNhacKhongLoi/LangNgheLoiChua(Saxophone)/ChuaLaConDuong_pxc.pdf</pdf>
	</song>
	<song>
		<albumid>1136</albumid>
		<songid>13983</songid>
		<name>Lời thiêng (Saxophone)</name>
		<artist>Đông Hòa</artist>
		<author>Xuân Tưởng</author>
		<album>Lắng Nghe Lời Chúa (Saxophone)</album>
		<type>Saxophone (Hòa Tấu)</type>
		<audio>http://thanhcavietnam.mobi/FilesNhacKhongLoi/LangNgheLoiChua(Saxophone)/08.LoiThieng_xt_DongHoa.mp3</audio>
		<pdf>http://thanhcavietnam.mobi/FilesNhacKhongLoi/LangNgheLoiChua(Saxophone)/LoiThieng_xt.pdf</pdf>
	</song>
	<song>
		<albumid>1136</albumid>
		<songid>13978</songid>
		<name>Trong trái tim Chúa (Saxophone)</name>
		<artist>Đông Hòa</artist>
		<author>Phanxicô</author>
		<album>Lắng Nghe Lời Chúa (Saxophone)</album>
		<type>Saxophone (Hòa Tấu)</type>
		<audio>http://thanhcavietnam.mobi/FilesNhacKhongLoi/LangNgheLoiChua(Saxophone)/03.TrongTraiTimChua_pxc_DongHoa.mp3</audio>
		<pdf>http://thanhcavietnam.mobi/FilesNhacKhongLoi/LangNgheLoiChua(Saxophone)/TrongTraiTimChua_pxc.pdf</pdf>
	</song>
	<song>
		<albumid>1136</albumid>
		<songid>13980</songid>
		<name>Lắng nghe lời Chúa (Saxophone)</name>
		<artist>Đông Hòa</artist>
		<author>Lm. Nguyễn Duy</author>
		<album>Lắng Nghe Lời Chúa (Saxophone)</album>
		<type>Saxophone (Hòa Tấu)</type>
		<audio>http://thanhcavietnam.mobi/FilesNhacKhongLoi/LangNgheLoiChua(Saxophone)/05.LangNgheLoiChua_nd_DongHoa.mp3</audio>
		<pdf>http://thanhcavietnam.mobi/FilesNhacKhongLoi/LangNgheLoiChua(Saxophone)/LangNgheLoiChua_nd.pdf</pdf>
	</song>
	<song>
		<albumid>1136</albumid>
		<songid>13976</songid>
		<name>Con đường Chúa đã qua (Saxophone)</name>
		<artist>Đông Hòa</artist>
		<author>Lm. Văn Chi</author>
		<album>Lắng Nghe Lời Chúa (Saxophone)</album>
		<type>Saxophone (Hòa Tấu)</type>
		<audio>http://thanhcavietnam.mobi/FilesNhacKhongLoi/LangNgheLoiChua(Saxophone)/01.ConDuongChuaDaQua_vc_DongHoa.mp3</audio>
		<pdf>http://thanhcavietnam.mobi/FilesNhacKhongLoi/LangNgheLoiChua(Saxophone)/ConDuongChuaDaQua_vc.pdf</pdf>
	</song>
	<song>
		<albumid>1136</albumid>
		<songid>13979</songid>
		<name>Chúng con cần đến Chúa (Saxophone)</name>
		<artist>Đông Hòa</artist>
		<author>Phanxicô</author>
		<album>Lắng Nghe Lời Chúa (Saxophone)</album>
		<type>Saxophone (Hòa Tấu)</type>
		<audio>http://thanhcavietnam.mobi/FilesNhacKhongLoi/LangNgheLoiChua(Saxophone)/04.ChungConCanDenChua_pxc_DongHoa.mp3</audio>
		<pdf>http://thanhcavietnam.mobi/FilesNhacKhongLoi/LangNgheLoiChua(Saxophone)/ChungConCanDenChua_pxc.pdf</pdf>
	</song>
	<song>
		<albumid>1136</albumid>
		<songid>13984</songid>
		<name>Luật yêu thương (Saxophone)</name>
		<artist>Đông Hòa</artist>
		<author>Lm. Nguyễn Duy</author>
		<album>Lắng Nghe Lời Chúa (Saxophone)</album>
		<type>Saxophone (Hòa Tấu)</type>
		<audio>http://thanhcavietnam.mobi/FilesNhacKhongLoi/LangNgheLoiChua(Saxophone)/09.LuatYeuThuong_nd_DongHoa.mp3</audio>
		<pdf>http://thanhcavietnam.mobi/FilesNhacKhongLoi/LangNgheLoiChua(Saxophone)/LuatYeuThuong_nd.pdf</pdf>
	</song>
	<song>
		<albumid>1136</albumid>
		<songid>13977</songid>
		<name>Lời kinh nguyện trầm (Saxophone)</name>
		<artist>Đông Hòa</artist>
		<author>Đỗ Vy Hạ</author>
		<album>Lắng Nghe Lời Chúa (Saxophone)</album>
		<type>Saxophone (Hòa Tấu)</type>
		<audio>http://thanhcavietnam.mobi/FilesNhacKhongLoi/LangNgheLoiChua(Saxophone)/02.LoiKinhNguyenTram_dvh_DongHoa.mp3</audio>
		<pdf>http://thanhcavietnam.mobi/FilesNhacKhongLoi/LangNgheLoiChua(Saxophone)/LoiKinhNguyenTram_dvh.pdf</pdf>
	</song>
	<song>
		<albumid>1136</albumid>
		<songid>13981</songid>
		<name>Lạy Chúa, Chúa đã thấy (Saxophone)</name>
		<artist>Đông Hòa</artist>
		<author>Lan Thanh</author>
		<album>Lắng Nghe Lời Chúa (Saxophone)</album>
		<type>Saxophone (Hòa Tấu)</type>
		<audio>http://thanhcavietnam.mobi/FilesNhacKhongLoi/LangNgheLoiChua(Saxophone)/06.LayChuaChuaDaThay_lt_DongHoa.mp3</audio>
		<pdf></pdf>
	</song>
</songs>